{
  "version": "5.1.1",
  "flags": {},
  "shapes": [
    {
      "label": "resistor",
      "points": [
        [
          82.0,
          199.0
        ],
        [
          121.0,
          219.0
        ]
      ],
      "group_id": null,
      "shape_type": "rectangle",
      "flags": {}
    },
    {
      "label": "gnd",
      "points": [
        [
          321.0,
          72.0
        ],
        [
          348.0,
          87.0
        ]
      ],
      "group_id": null,
      "shape_type": "rectangle",
      "flags": {}
    },
    {
      "label": "resistor",
      "points": [
        [
          237.0,
          277.0
        ],
        [
          256.0,
          315.0
        ]
      ],
      "group_id": null,
      "shape_type": "rectangle",
      "flags": {}
    },
    {
      "label": "resistor",
      "points": [
        [
          238.0,
          132.0
        ],
        [
          255.0,
          168.0
        ]
      ],
      "group_id": null,
      "shape_type": "rectangle",
      "flags": {}
    },
    {
      "label": "npn",
      "points": [
        [
          278.0,
          199.0
        ],
        [
          309.0,
          250.0
        ]
      ],
      "group_id": null,
      "shape_type": "rectangle",
      "flags": {}
    },
    {
      "label": "resistor2",
      "points": [
        [
          458.0,
          277.0
        ],
        [
          475.0,
          317.0
        ]
      ],
      "group_id": null,
      "shape_type": "rectangle",
      "flags": {}
    },
    {
      "label": "capacitor",
      "points": [
        [
          347.0,
          290.0
        ],
        [
          381.0,
          303.0
        ]
      ],
      "group_id": null,
      "shape_type": "rectangle",
      "flags": {}
    },
    {
      "label": "gnd",
      "points": [
        [
          262.0,
          350.0
        ],
        [
          290.0,
          367.0
        ]
      ],
      "group_id": null,
      "shape_type": "rectangle",
      "flags": {}
    },
    {
      "label": "resistor",
      "points": [
        [
          298.0,
          132.0
        ],
        [
          315.0,
          169.0
        ]
      ],
      "group_id": null,
      "shape_type": "rectangle",
      "flags": {}
    },
    {
      "label": "capacitor",
      "points": [
        [
          372.0,
          178.0
        ],
        [
          384.0,
          211.0
        ]
      ],
      "group_id": null,
      "shape_type": "rectangle",
      "flags": {}
    },
    {
      "label": "resistor",
      "points": [
        [
          296.0,
          278.0
        ],
        [
          314.0,
          315.0
        ]
      ],
      "group_id": null,
      "shape_type": "rectangle",
      "flags": {}
    },
    {
      "label": "voltage",
      "points": [
        [
          40.0,
          265.0
        ],
        [
          73.0,
          298.0
        ]
      ],
      "group_id": null,
      "shape_type": "rectangle",
      "flags": {}
    },
    {
      "label": "capacitor",
      "points": [
        [
          182.0,
          206.0
        ],
        [
          195.0,
          241.0
        ]
      ],
      "group_id": null,
      "shape_type": "rectangle",
      "flags": {}
    },
    {
      "label": "voltage-lines",
      "points": [
        [
          282.0468,
          45.4821
        ],
        [
          323.6364,
          80.0292
        ]
      ],
      "group_id": null,
      "shape_type": "rectangle",
      "flags": {}
    },
    {
      "label": "port",
      "points": [
        [
          125.4967,
          181.1463
        ],
        [
          150.5137,
          212.1539
        ]
      ],
      "group_id": null,
      "shape_type": "rectangle",
      "flags": {}
    },
    {
      "label": "port",
      "points": [
        [
          463.9004,
          239.999
        ],
        [
          493.5172,
          268.9387
        ]
      ],
      "group_id": null,
      "shape_type": "rectangle",
      "flags": {}
    }
  ],
  "imagePath": "1281.jpg",
  "imageData": null,
  "imageHeight": 405,
  "imageWidth": 540
}