{
  "version": "5.1.1",
  "flags": {},
  "shapes": [
    {
      "label": "resistor",
      "points": [
        [
          229.0,
          77.0
        ],
        [
          249.0,
          118.0
        ]
      ],
      "group_id": null,
      "shape_type": "rectangle",
      "flags": {}
    },
    {
      "label": "gnd",
      "points": [
        [
          105.0,
          208.0
        ],
        [
          128.0,
          221.0
        ]
      ],
      "group_id": null,
      "shape_type": "rectangle",
      "flags": {}
    },
    {
      "label": "gnd",
      "points": [
        [
          304.0,
          198.0
        ],
        [
          328.0,
          210.0
        ]
      ],
      "group_id": null,
      "shape_type": "rectangle",
      "flags": {}
    },
    {
      "label": "gnd",
      "points": [
        [
          145.0,
          325.0
        ],
        [
          168.0,
          337.0
        ]
      ],
      "group_id": null,
      "shape_type": "rectangle",
      "flags": {}
    },
    {
      "label": "gnd",
      "points": [
        [
          34.0,
          324.0
        ],
        [
          57.0,
          336.0
        ]
      ],
      "group_id": null,
      "shape_type": "rectangle",
      "flags": {}
    },
    {
      "label": "resistor",
      "points": [
        [
          64.0,
          239.0
        ],
        [
          103.0,
          259.0
        ]
      ],
      "group_id": null,
      "shape_type": "rectangle",
      "flags": {}
    },
    {
      "label": "capacitor",
      "points": [
        [
          303.0,
          286.0
        ],
        [
          327.0,
          299.0
        ]
      ],
      "group_id": null,
      "shape_type": "rectangle",
      "flags": {}
    },
    {
      "label": "resistor",
      "points": [
        [
          230.0,
          276.0
        ],
        [
          248.0,
          315.0
        ]
      ],
      "group_id": null,
      "shape_type": "rectangle",
      "flags": {}
    },
    {
      "label": "gnd",
      "points": [
        [
          304.0,
          324.0
        ],
        [
          327.0,
          336.0
        ]
      ],
      "group_id": null,
      "shape_type": "rectangle",
      "flags": {}
    },
    {
      "label": "port",
      "points": [
        [
          233.0,
          325.0
        ],
        [
          245.0,
          336.0
        ]
      ],
      "group_id": null,
      "shape_type": "rectangle",
      "flags": {}
    },
    {
      "label": "resistor",
      "points": [
        [
          147.0,
          78.0
        ],
        [
          167.0,
          118.0
        ]
      ],
      "group_id": null,
      "shape_type": "rectangle",
      "flags": {}
    },
    {
      "label": "capacitor",
      "points": [
        [
          104.0,
          168.0
        ],
        [
          129.0,
          182.0
        ]
      ],
      "group_id": null,
      "shape_type": "rectangle",
      "flags": {}
    },
    {
      "label": "port",
      "points": [
        [
          193.0,
          23.0
        ],
        [
          203.0,
          34.0
        ]
      ],
      "group_id": null,
      "shape_type": "rectangle",
      "flags": {}
    },
    {
      "label": "resistor",
      "points": [
        [
          147.0,
          183.0
        ],
        [
          167.0,
          223.0
        ]
      ],
      "group_id": null,
      "shape_type": "rectangle",
      "flags": {}
    },
    {
      "label": "pmos",
      "points": [
        [
          219.0,
          137.0
        ],
        [
          240.0,
          166.0
        ]
      ],
      "group_id": null,
      "shape_type": "rectangle",
      "flags": {}
    },
    {
      "label": "capacitor",
      "points": [
        [
          270.0,
          112.0
        ],
        [
          283.0,
          135.0
        ]
      ],
      "group_id": null,
      "shape_type": "rectangle",
      "flags": {}
    },
    {
      "label": "capacitor",
      "points": [
        [
          117.0,
          237.0
        ],
        [
          130.0,
          260.0
        ]
      ],
      "group_id": null,
      "shape_type": "rectangle",
      "flags": {}
    },
    {
      "label": "resistor",
      "points": [
        [
          147.0,
          271.0
        ],
        [
          166.0,
          311.0
        ]
      ],
      "group_id": null,
      "shape_type": "rectangle",
      "flags": {}
    },
    {
      "label": "resistor",
      "points": [
        [
          307.0,
          145.0
        ],
        [
          325.0,
          184.0
        ]
      ],
      "group_id": null,
      "shape_type": "rectangle",
      "flags": {}
    },
    {
      "label": "voltage",
      "points": [
        [
          29.0,
          266.0
        ],
        [
          61.0,
          299.0
        ]
      ],
      "group_id": null,
      "shape_type": "rectangle",
      "flags": {}
    },
    {
      "label": "port",
      "points": [
        [
          341.0,
          118.0
        ],
        [
          352.0,
          129.0
        ]
      ],
      "group_id": null,
      "shape_type": "rectangle",
      "flags": {}
    },
    {
      "label": "nmos",
      "points": [
        [
          217.4988,
          235.4886
        ],
        [
          242.1013,
          264.4814
        ]
      ],
      "group_id": null,
      "shape_type": "rectangle",
      "flags": {}
    }
  ],
  "imagePath": "5141.jpg",
  "imageData": null,
  "imageHeight": 371,
  "imageWidth": 425
}