{
  "version": "5.1.1",
  "flags": {},
  "shapes": [
    {
      "label": "port",
      "points": [
        [
          585.0,
          222.0
        ],
        [
          609.0,
          246.0
        ]
      ],
      "group_id": null,
      "shape_type": "rectangle",
      "flags": {}
    },
    {
      "label": "port",
      "points": [
        [
          96.0,
          186.0
        ],
        [
          106.0,
          197.0
        ]
      ],
      "group_id": null,
      "shape_type": "rectangle",
      "flags": {}
    },
    {
      "label": "gnd",
      "points": [
        [
          328.0,
          439.0
        ],
        [
          379.0,
          467.0
        ]
      ],
      "group_id": null,
      "shape_type": "rectangle",
      "flags": {}
    },
    {
      "label": "nmos",
      "points": [
        [
          200.0,
          289.0
        ],
        [
          274.0,
          349.0
        ]
      ],
      "group_id": null,
      "shape_type": "rectangle",
      "flags": {}
    },
    {
      "label": "nmos",
      "points": [
        [
          369.0,
          290.0
        ],
        [
          442.0,
          350.0
        ]
      ],
      "group_id": null,
      "shape_type": "rectangle",
      "flags": {}
    },
    {
      "label": "pmos",
      "points": [
        [
          370.0,
          75.0
        ],
        [
          436.7004,
          134.0
        ]
      ],
      "group_id": null,
      "shape_type": "rectangle",
      "flags": {}
    },
    {
      "label": "pmos",
      "points": [
        [
          371.0,
          159.0
        ],
        [
          437.3074,
          218.0
        ]
      ],
      "group_id": null,
      "shape_type": "rectangle",
      "flags": {}
    },
    {
      "label": "port",
      "points": [
        [
          437.1271,
          187.0508
        ],
        [
          443.8057,
          194.6153
        ]
      ],
      "group_id": null,
      "shape_type": "rectangle",
      "flags": {}
    },
    {
      "label": "port",
      "points": [
        [
          388.2901,
          15.4274
        ],
        [
          401.8625,
          29.5273
        ]
      ],
      "group_id": null,
      "shape_type": "rectangle",
      "flags": {}
    },
    {
      "label": "port",
      "points": [
        [
          93.8424,
          97.3926
        ],
        [
          103.7684,
          111.4802
        ]
      ],
      "group_id": null,
      "shape_type": "rectangle",
      "flags": {}
    },
    {
      "label": "port",
      "points": [
        [
          435.9103,
          102.4669
        ],
        [
          441.9978,
          109.4153
        ]
      ],
      "group_id": null,
      "shape_type": "rectangle",
      "flags": {}
    }
  ],
  "imagePath": "A compact switched capacitor-regulated charge pump power supply_12.jpg",
  "imageData": null,
  "imageHeight": 473,
  "imageWidth": 692
}