{
  "version": "5.1.1",
  "flags": {},
  "shapes": [
    {
      "label": "resistor",
      "points": [
        [
          521.857,
          95.8607
        ],
        [
          557.8576,
          150.862
        ]
      ],
      "group_id": null,
      "shape_type": "rectangle",
      "flags": {}
    },
    {
      "label": "gnd",
      "points": [
        [
          520.0926,
          322.3165
        ],
        [
          561.0954,
          344.3155
        ]
      ],
      "group_id": null,
      "shape_type": "rectangle",
      "flags": {}
    },
    {
      "label": "resistor",
      "points": [
        [
          521.4731,
          232.1146
        ],
        [
          557.4777,
          287.1168
        ]
      ],
      "group_id": null,
      "shape_type": "rectangle",
      "flags": {}
    },
    {
      "label": "current",
      "points": [
        [
          396.6096,
          100.1985
        ],
        [
          453.7878,
          156.2183
        ]
      ],
      "group_id": null,
      "shape_type": "rectangle",
      "flags": {}
    },
    {
      "label": "current",
      "points": [
        [
          7.2215,
          98.3398
        ],
        [
          64.3904,
          154.3552
        ]
      ],
      "group_id": null,
      "shape_type": "rectangle",
      "flags": {}
    },
    {
      "label": "gnd",
      "points": [
        [
          13.4484,
          196.4904
        ],
        [
          54.4432,
          218.4952
        ]
      ],
      "group_id": null,
      "shape_type": "rectangle",
      "flags": {}
    },
    {
      "label": "resistor",
      "points": [
        [
          290.3052,
          97.7206
        ],
        [
          326.3029,
          152.7211
        ]
      ],
      "group_id": null,
      "shape_type": "rectangle",
      "flags": {}
    },
    {
      "label": "gnd",
      "points": [
        [
          623.5847,
          80.348
        ],
        [
          664.5881,
          102.3428
        ]
      ],
      "group_id": null,
      "shape_type": "rectangle",
      "flags": {}
    },
    {
      "label": "port",
      "points": [
        [
          639.6725,
          183.9061
        ],
        [
          655.1904,
          202.0557
        ]
      ],
      "group_id": null,
      "shape_type": "rectangle",
      "flags": {}
    },
    {
      "label": "gnd",
      "points": [
        [
          147.3859,
          195.8656
        ],
        [
          188.3845,
          217.8606
        ]
      ],
      "group_id": null,
      "shape_type": "rectangle",
      "flags": {}
    },
    {
      "label": "gnd",
      "points": [
        [
          624.6725,
          320.9548
        ],
        [
          665.6739,
          342.9575
        ]
      ],
      "group_id": null,
      "shape_type": "rectangle",
      "flags": {}
    },
    {
      "label": "port",
      "points": [
        [
          636.1342,
          262.5805
        ],
        [
          651.646,
          280.7311
        ]
      ],
      "group_id": null,
      "shape_type": "rectangle",
      "flags": {}
    },
    {
      "label": "port",
      "points": [
        [
          162.0585,
          127.2227
        ],
        [
          177.5761,
          145.3714
        ]
      ],
      "group_id": null,
      "shape_type": "rectangle",
      "flags": {}
    }
  ],
  "imagePath": "book_Analysis_image_172.png",
  "imageData": null,
  "imageHeight": 356,
  "imageWidth": 680
}