{
  "version": "5.1.1",
  "flags": {},
  "shapes": [
    {
      "label": "cross-line-curved",
      "points": [
        [
          356.8134,
          965.7276
        ],
        [
          395.886,
          995.9679
        ]
      ],
      "group_id": null,
      "shape_type": "rectangle",
      "flags": {}
    },
    {
      "label": "port",
      "points": [
        [
          668.8738,
          97.2696
        ],
        [
          684.4228,
          115.2459
        ]
      ],
      "group_id": null,
      "shape_type": "rectangle",
      "flags": {}
    },
    {
      "label": "port",
      "points": [
        [
          629.8812,
          100.7298
        ],
        [
          645.4324,
          118.7155
        ]
      ],
      "group_id": null,
      "shape_type": "rectangle",
      "flags": {}
    },
    {
      "label": "port",
      "points": [
        [
          409.8055,
          166.5714
        ],
        [
          425.3689,
          184.5644
        ]
      ],
      "group_id": null,
      "shape_type": "rectangle",
      "flags": {}
    },
    {
      "label": "port",
      "points": [
        [
          38.9724,
          235.8954
        ],
        [
          54.5393,
          253.8734
        ]
      ],
      "group_id": null,
      "shape_type": "rectangle",
      "flags": {}
    },
    {
      "label": "port",
      "points": [
        [
          408.9468,
          236.7541
        ],
        [
          424.4987,
          254.7496
        ]
      ],
      "group_id": null,
      "shape_type": "rectangle",
      "flags": {}
    },
    {
      "label": "port",
      "points": [
        [
          614.2891,
          257.558
        ],
        [
          629.8429,
          275.5387
        ]
      ],
      "group_id": null,
      "shape_type": "rectangle",
      "flags": {}
    },
    {
      "label": "port",
      "points": [
        [
          972.1266,
          259.2889
        ],
        [
          987.6813,
          277.2724
        ]
      ],
      "group_id": null,
      "shape_type": "rectangle",
      "flags": {}
    },
    {
      "label": "port",
      "points": [
        [
          930.5333,
          449.031
        ],
        [
          946.0915,
          467.0293
        ]
      ],
      "group_id": null,
      "shape_type": "rectangle",
      "flags": {}
    },
    {
      "label": "port",
      "points": [
        [
          664.5412,
          449.0348
        ],
        [
          680.0975,
          467.0218
        ]
      ],
      "group_id": null,
      "shape_type": "rectangle",
      "flags": {}
    },
    {
      "label": "port",
      "points": [
        [
          249.5159,
          448.1628
        ],
        [
          265.071,
          466.1575
        ]
      ],
      "group_id": null,
      "shape_type": "rectangle",
      "flags": {}
    },
    {
      "label": "port",
      "points": [
        [
          207.0621,
          446.4352
        ],
        [
          222.6141,
          464.4212
        ]
      ],
      "group_id": null,
      "shape_type": "rectangle",
      "flags": {}
    },
    {
      "label": "port",
      "points": [
        [
          100.4992,
          338.1329
        ],
        [
          116.0499,
          356.1173
        ]
      ],
      "group_id": null,
      "shape_type": "rectangle",
      "flags": {}
    },
    {
      "label": "nmos",
      "points": [
        [
          340.8162,
          213.8684
        ],
        [
          400.4691,
          280.6588
        ]
      ],
      "group_id": null,
      "shape_type": "rectangle",
      "flags": {}
    },
    {
      "label": "current",
      "points": [
        [
          127.1107,
          715.423
        ],
        [
          181.2608,
          770.3002
        ]
      ],
      "group_id": null,
      "shape_type": "rectangle",
      "flags": {}
    },
    {
      "label": "cross-line-curved",
      "points": [
        [
          356.6878,
          843.8298
        ],
        [
          395.7497,
          874.0614
        ]
      ],
      "group_id": null,
      "shape_type": "rectangle",
      "flags": {}
    },
    {
      "label": "port",
      "points": [
        [
          86.6848,
          615.0477
        ],
        [
          102.246,
          633.0395
        ]
      ],
      "group_id": null,
      "shape_type": "rectangle",
      "flags": {}
    },
    {
      "label": "port",
      "points": [
        [
          933.6309,
          615.894
        ],
        [
          949.1948,
          633.8776
        ]
      ],
      "group_id": null,
      "shape_type": "rectangle",
      "flags": {}
    },
    {
      "label": "port",
      "points": [
        [
          918.7521,
          976.1825
        ],
        [
          934.314,
          994.1603
        ]
      ],
      "group_id": null,
      "shape_type": "rectangle",
      "flags": {}
    },
    {
      "label": "port",
      "points": [
        [
          930.889,
          1094.8803
        ],
        [
          946.4415,
          1112.8615
        ]
      ],
      "group_id": null,
      "shape_type": "rectangle",
      "flags": {}
    },
    {
      "label": "port",
      "points": [
        [
          603.3788,
          736.1785
        ],
        [
          618.9346,
          754.1684
        ]
      ],
      "group_id": null,
      "shape_type": "rectangle",
      "flags": {}
    },
    {
      "label": "port",
      "points": [
        [
          404.9612,
          727.5126
        ],
        [
          420.5138,
          745.5061
        ]
      ],
      "group_id": null,
      "shape_type": "rectangle",
      "flags": {}
    },
    {
      "label": "port",
      "points": [
        [
          90.4492,
          976.1837
        ],
        [
          106.0,
          994.1657
        ]
      ],
      "group_id": null,
      "shape_type": "rectangle",
      "flags": {}
    },
    {
      "label": "port",
      "points": [
        [
          86.1128,
          1097.4852
        ],
        [
          101.6685,
          1115.4639
        ]
      ],
      "group_id": null,
      "shape_type": "rectangle",
      "flags": {}
    },
    {
      "label": "port",
      "points": [
        [
          58.9081,
          338.1388
        ],
        [
          74.4529,
          356.1158
        ]
      ],
      "group_id": null,
      "shape_type": "rectangle",
      "flags": {}
    },
    {
      "label": "vdd",
      "points": [
        [
          337.1584,
          48.0493
        ],
        [
          358.2193,
          67.8978
        ]
      ],
      "group_id": null,
      "shape_type": "rectangle",
      "flags": {}
    },
    {
      "label": "vdd",
      "points": [
        [
          113.6137,
          46.5435
        ],
        [
          134.6727,
          66.4082
        ]
      ],
      "group_id": null,
      "shape_type": "rectangle",
      "flags": {}
    },
    {
      "label": "vdd",
      "points": [
        [
          793.5217,
          48.3563
        ],
        [
          814.5813,
          68.2116
        ]
      ],
      "group_id": null,
      "shape_type": "rectangle",
      "flags": {}
    },
    {
      "label": "vdd",
      "points": [
        [
          143.829,
          615.7765
        ],
        [
          164.8818,
          635.631
        ]
      ],
      "group_id": null,
      "shape_type": "rectangle",
      "flags": {}
    },
    {
      "label": "vdd",
      "points": [
        [
          369.8256,
          614.3328
        ],
        [
          390.8816,
          634.1909
        ]
      ],
      "group_id": null,
      "shape_type": "rectangle",
      "flags": {}
    },
    {
      "label": "vdd",
      "points": [
        [
          641.3073,
          615.0541
        ],
        [
          662.3615,
          634.9133
        ]
      ],
      "group_id": null,
      "shape_type": "rectangle",
      "flags": {}
    },
    {
      "label": "vdd",
      "points": [
        [
          860.8089,
          615.7751
        ],
        [
          881.8681,
          635.6318
        ]
      ],
      "group_id": null,
      "shape_type": "rectangle",
      "flags": {}
    },
    {
      "label": "pmos",
      "points": [
        [
          116.3342,
          79.7407
        ],
        [
          175.9733,
          146.5262
        ]
      ],
      "group_id": null,
      "shape_type": "rectangle",
      "flags": {}
    },
    {
      "label": "pmos",
      "points": [
        [
          293.9588,
          78.2947
        ],
        [
          353.5927,
          145.0847
        ]
      ],
      "group_id": null,
      "shape_type": "rectangle",
      "flags": {}
    },
    {
      "label": "pmos",
      "points": [
        [
          751.7148,
          102.8476
        ],
        [
          811.3675,
          169.6369
        ]
      ],
      "group_id": null,
      "shape_type": "rectangle",
      "flags": {}
    },
    {
      "label": "pmos",
      "points": [
        [
          640.5243,
          234.9747
        ],
        [
          700.1652,
          301.7669
        ]
      ],
      "group_id": null,
      "shape_type": "rectangle",
      "flags": {}
    },
    {
      "label": "pmos",
      "points": [
        [
          906.2359,
          236.4239
        ],
        [
          965.8716,
          303.205
        ]
      ],
      "group_id": null,
      "shape_type": "rectangle",
      "flags": {}
    },
    {
      "label": "pmos",
      "points": [
        [
          820.3129,
          650.8617
        ],
        [
          879.9541,
          717.6578
        ]
      ],
      "group_id": null,
      "shape_type": "rectangle",
      "flags": {}
    },
    {
      "label": "pmos",
      "points": [
        [
          638.3539,
          650.8671
        ],
        [
          698.0,
          717.6515
        ]
      ],
      "group_id": null,
      "shape_type": "rectangle",
      "flags": {}
    },
    {
      "label": "pmos",
      "points": [
        [
          325.7284,
          653.033
        ],
        [
          385.3689,
          719.8186
        ]
      ],
      "group_id": null,
      "shape_type": "rectangle",
      "flags": {}
    },
    {
      "label": "pmos",
      "points": [
        [
          324.2712,
          753.3926
        ],
        [
          383.9293,
          820.1833
        ]
      ],
      "group_id": null,
      "shape_type": "rectangle",
      "flags": {}
    },
    {
      "label": "pmos",
      "points": [
        [
          639.0846,
          772.8905
        ],
        [
          698.7255,
          839.6773
        ]
      ],
      "group_id": null,
      "shape_type": "rectangle",
      "flags": {}
    },
    {
      "label": "pmos",
      "points": [
        [
          818.1492,
          773.614
        ],
        [
          877.7843,
          840.3974
        ]
      ],
      "group_id": null,
      "shape_type": "rectangle",
      "flags": {}
    },
    {
      "label": "nmos",
      "points": [
        [
          145.1163,
          891.7823
        ],
        [
          204.7566,
          958.5799
        ]
      ],
      "group_id": null,
      "shape_type": "rectangle",
      "flags": {}
    },
    {
      "label": "nmos",
      "points": [
        [
          145.6148,
          1012.1205
        ],
        [
          205.2502,
          1078.907
        ]
      ],
      "group_id": null,
      "shape_type": "rectangle",
      "flags": {}
    },
    {
      "label": "nmos",
      "points": [
        [
          326.124,
          1011.6264
        ],
        [
          385.7601,
          1078.4041
        ]
      ],
      "group_id": null,
      "shape_type": "rectangle",
      "flags": {}
    },
    {
      "label": "nmos",
      "points": [
        [
          323.6166,
          889.2736
        ],
        [
          383.2506,
          956.0611
        ]
      ],
      "group_id": null,
      "shape_type": "rectangle",
      "flags": {}
    },
    {
      "label": "nmos",
      "points": [
        [
          598.385,
          892.7885
        ],
        [
          658.0317,
          959.5733
        ]
      ],
      "group_id": null,
      "shape_type": "rectangle",
      "flags": {}
    },
    {
      "label": "nmos",
      "points": [
        [
          596.3897,
          1013.6218
        ],
        [
          656.027,
          1080.4167
        ]
      ],
      "group_id": null,
      "shape_type": "rectangle",
      "flags": {}
    },
    {
      "label": "nmos",
      "points": [
        [
          821.0193,
          893.7992
        ],
        [
          880.6508,
          960.5765
        ]
      ],
      "group_id": null,
      "shape_type": "rectangle",
      "flags": {}
    },
    {
      "label": "nmos",
      "points": [
        [
          821.5164,
          1013.1281
        ],
        [
          881.1578,
          1079.9173
        ]
      ],
      "group_id": null,
      "shape_type": "rectangle",
      "flags": {}
    },
    {
      "label": "nmos",
      "points": [
        [
          683.3923,
          367.8204
        ],
        [
          743.0493,
          434.6194
        ]
      ],
      "group_id": null,
      "shape_type": "rectangle",
      "flags": {}
    },
    {
      "label": "nmos",
      "points": [
        [
          865.4185,
          368.8331
        ],
        [
          925.0533,
          435.614
        ]
      ],
      "group_id": null,
      "shape_type": "rectangle",
      "flags": {}
    },
    {
      "label": "nmos",
      "points": [
        [
          184.5486,
          347.9904
        ],
        [
          244.1846,
          414.7736
        ]
      ],
      "group_id": null,
      "shape_type": "rectangle",
      "flags": {}
    },
    {
      "label": "nmos",
      "points": [
        [
          72.5651,
          215.1105
        ],
        [
          132.2026,
          281.9097
        ]
      ],
      "group_id": null,
      "shape_type": "rectangle",
      "flags": {}
    }
  ],
  "imagePath": "book_Analysis_image_409.png",
  "imageData": null,
  "imageHeight": 1204,
  "imageWidth": 1028
}